{
    "meta": {
        "label": "Certificates",
        "description": "",
        "icon": "icon-cloud"
    },
    "defaultDefinableInline": true,
    "defaultDefinableAtProjectLevel": true,
    "pluginParams": [],
    "params": [
        {
            "name": "sharepoint_tenant",
            "label": "Tenant",
            "type": "STRING",
            "description": "As in <tenant>.sharepoint.com. Please refer to plugin doc.",
            "mandatory": true
        },
        {
            "name": "sharepoint_site",
            "label": "Site path",
            "type": "STRING",
            "description": "sites/site_name/subsite...",
            "mandatory": true
        },
        {
            "name": "sharepoint_root",
            "label": "Root directory",
            "type": "STRING",
            "description": "",
            "defaultValue": "Shared Documents"
        },
        {
            "name": "tenant_id",
            "label": "Tenant ID",
            "type": "STRING",
            "description": "",
            "mandatory": true
        },
        {
            "name": "client_id",
            "label": "Client ID",
            "type": "STRING",
            "description": "",
            "mandatory": true
        },
        {
            "name": "client_certificate_thumbprint",
            "label": "Client certificate thumbprint",
            "type": "STRING",
            "description": "",
            "mandatory": true
        },
        {
            "name": "client_certificate",
            "label": "Client certificate (private key)",
            "type": "PASSWORD",
            "description": "Base64-encoded, starting with '-----BEGIN PRIVATE KEY-----'",
            "mandatory": true
        },
        {
            "name": "passphrase",
            "label": "Certificate passphrase",
            "type": "PASSWORD",
            "description": "If required by private key",
            "mandatory": false
        },
        {
            "name": "activate_libraries_whitelist",
            "label": "Whitelists libraries",
            "type": "BOOLEAN",
            "description": "Not advised: access rights should be handled at Azure app level"
        },
        {
            "name": "libraries_whitelist",
            "label": "Whitelisted libraries",
            "type": "OBJECT_LIST",
            "description": "",
            "visibilityCondition": "model.activate_libraries_whitelist === true",
            "subParams": [
                {
                    "name": "whitelist_name",
                    "label": "Library name",
                    "type": "STRING",
                    "description": "/sites/YourSite/Shared Documents/your folder path"
                },
                {
                    "name": "whitelist_rights",
                    "label": "Access rights",
                    "type": "MULTISELECT",
                    "description": "",
                    "selectChoices": [
                        {
                            "value": "read",
                            "label": "Read"
                        },
                        {
                            "value": "write",
                            "label": "Write"
                        }
                    ]
                }
            ]
        },
        {
            "name": "activate_lists_whitelist",
            "label": "Whitelists lists",
            "type": "BOOLEAN",
            "description": "Not advised: access rights should be handled at Azure app level"
        },
        {
            "name": "lists_whitelist",
            "label": "Whitelisted lists",
            "type": "OBJECT_LIST",
            "description": "",
            "visibilityCondition": "model.activate_lists_whitelist === true",
            "subParams": [
                {
                    "name": "whitelist_name",
                    "label": "List name",
                    "type": "STRING",
                    "description": "List ID from the list's SharePoint URL"
                },
                {
                    "name": "whitelist_rights",
                    "label": "Access rights",
                    "type": "MULTISELECT",
                    "description": "",
                    "selectChoices": [
                        {
                            "value": "read",
                            "label": "Read"
                        },
                        {
                            "value": "write",
                            "label": "Write"
                        }
                    ]
                }
            ]
        }
    ]
}